LICENSE
README.md
setup.cfg
setup.py
idbadapter/__init__.py
idbadapter/models.py
idbadapter/mschm.py
idbadapter/schedule_loader.py
idbadapter.egg-info/PKG-INFO
idbadapter.egg-info/SOURCES.txt
idbadapter.egg-info/dependency_links.txt
idbadapter.egg-info/requires.txt
idbadapter.egg-info/top_level.txt
idbadapter/field_dev/__init__.py
idbadapter/field_dev/history.py
idbadapter/field_dev/__init__.py
idbadapter/field_dev/history.py