Metadata-Version: 2.1
Name: idbadapter
Version: 2.3.14
Summary: Adapter for database access
Home-page: https://github.com/AnatolyPershinov/gpn_cache_module
Download-URL: https://github.com/AnatolyPershinov/gpn_cache_module/archive/master.zip
Author: Anatoly Pershinov
Author-email: anatoliypershinov@gmail.com
Classifier: License :: OSI Approved :: Apache Software License
Classifier: Operating System :: OS Independent
Classifier: Intended Audience :: End Users/Desktop
Classifier: Intended Audience :: Developers
Classifier: Programming Language :: Python
Classifier: Programming Language :: Python :: 3
License-File: LICENSE
